teaching_example/__init__.py
teaching_example/teaching_example.py
teaching_example-0.1.0.dist-info/AUTHORS.rst
teaching_example-0.1.0.dist-info/LICENSE
teaching_example-0.1.0.dist-info/METADATA
teaching_example-0.1.0.dist-info/WHEEL
teaching_example-0.1.0.dist-info/top_level.txt
teaching_example-0.1.0.dist-info/RECORD
