Metadata-Version: 2.1
Name: teaching-example
Version: 0.1.0
Summary: Making a cookiecutter example for teaching.
Home-page: https://github.com/Andesha/teaching_example
Author: Tyler Collins
Author-email: tk11br@sharcnet.ca
License: MIT license
Keywords: teaching_example
Platform: UNKNOWN
Classifier: Development Status :: 2 - Pre-Alpha
Classifier: Intended Audience :: Developers
Classifier: License :: OSI Approved :: MIT License
Classifier: Natural Language :: English
Classifier: Programming Language :: Python :: 3
Classifier: Programming Language :: Python :: 3.6
Classifier: Programming Language :: Python :: 3.7
Classifier: Programming Language :: Python :: 3.8
Requires-Python: >=3.6
License-File: LICENSE
License-File: AUTHORS.rst
